<?xml version="1.0" encoding="UTF-8" standalone="no"?>
<servico xmlns="http://servicos.gov.br/v3/schema" xmlns:xsi="http://www.w3.org/2001/XMLSchema-instance" xsi:schemaLocation="http://servicos.gov.br/v3/schema ../servico.xsd">
    <nome><![CDATA[teste servico]]></nome>
    <sigla>ts</sigla>
    <nomes-populares>
        <item>tt</item>
    </nomes-populares>
    <descricao><![CDATA[dasdsdasd]]></descricao>
    <contato/>
    <gratuito>false</gratuito>
    <solicitantes>
        <solicitante>
            <tipo>solici</tipo>
            <requisitos/>
        </solicitante>
    </solicitantes>
    <tempo-total-estimado>
        <ate max="2" unidade="dias-corridos"/>
        <descricao/>
    </tempo-total-estimado>
    <etapas>
        <etapa>
            <titulo>sadasdsadsadasd</titulo>
            <descricao/>
            <documentos>
                <default/>
            </documentos>
            <custos>
                <default/>
            </custos>
            <canais-de-prestacao>
                <default>
                    <canal-de-prestacao tipo="e-mail">
                        <descricao><![CDATA[sdsadsad]]></descricao>
                    </canal-de-prestacao>
                </default>
            </canais-de-prestacao>
        </etapa>
    </etapas>
    <orgao id="http://estruturaorganizacional.dados.gov.br/id/unidade-organizacional/123676"/>
    <segmentos-da-sociedade>
        <item>Órgãos e entidades públicas</item>
        <item>Demais segmentos (ONGs, organizações sociais, etc)</item>
    </segmentos-da-sociedade>
    <areas-de-interesse>
        <item>Assistência ao Portador de Deficiência</item>
        <item>Urbanismo</item>
        <item>Vigilância Sanitária</item>
    </areas-de-interesse>
    <palavras-chave>
        <item>sadasd</item>
        <item>sadsad</item>
        <item>sdasdasd</item>
    </palavras-chave>
    <legislacoes>
        <item><![CDATA[lei]]></item>
    </legislacoes>
</servico>
